bencode_rs/__init__.py
bencode_rs/__init__.pyi
bencode_rs/_bencode.abi3.so
bencode_rs/py.typed
bencode_rs-0.0.8.dist-info/METADATA
bencode_rs-0.0.8.dist-info/WHEEL
bencode_rs-0.0.8.dist-info/licenses/LICENSE
bencode_rs-0.0.8.dist-info/RECORD
