Metadata-Version: 2.4
Name: bencode-rs
Version: 0.0.8
Classifier: Development Status :: 2 - Pre-Alpha
Classifier: License :: OSI Approved :: MIT License
Classifier: Programming Language :: Rust
Classifier: Programming Language :: Python
Classifier: Programming Language :: Python :: 3
Classifier: Programming Language :: Python :: 3 :: Only
Classifier: Programming Language :: Python :: 3.10
Classifier: Programming Language :: Python :: 3.11
Classifier: Programming Language :: Python :: 3.12
Classifier: Programming Language :: Python :: 3.13
Classifier: Programming Language :: Python :: 3.14
Classifier: Programming Language :: Python :: Implementation :: CPython
License-File: LICENSE
Summary: a bencode parser build with pyo3
Keywords: bittorrent,bencode,p2p
Requires-Python: >=3.10, <4
Project-URL: Homepage, https://github.com/trim21/bencode-rs
